bccmaths/__init__.py
dictplus/__init__.py
listplus/__init__.py
strmaths/__init__.py
strmaths/basicSM.py
strplus/__init__.py
bbyc_pyplus-0.1.0.dist-info/METADATA
bbyc_pyplus-0.1.0.dist-info/WHEEL
bbyc_pyplus-0.1.0.dist-info/top_level.txt
bbyc_pyplus-0.1.0.dist-info/RECORD
