Metadata-Version: 2.1
Name: bbyc-pyplus
Version: 0.1.0
Summary: A collection of Python utility functions and extensions
Home-page: https://github.com/dhjs0000/PyPlus
Author: bbyc
Classifier: Programming Language :: Python :: 3
Classifier: License :: OSI Approved :: MIT License
Classifier: Operating System :: OS Independent
Requires-Python: >=3.6
